starlive/__init__.py
starlive/cli.py
starlive/detection.py
starlive/scripts.py
starlive/streams.py
starlive/types.py
starlive/websocket.py
starlive-0.2.0.dist-info/METADATA
starlive-0.2.0.dist-info/WHEEL
starlive-0.2.0.dist-info/entry_points.txt
starlive-0.2.0.dist-info/licenses/LICENSE
starlive-0.2.0.dist-info/RECORD
