Metadata-Version: 2.4
Name: starlive
Version: 0.2.0
Summary: Universal Hypermedia System for Starlette & FastAPI
License: Apache-2.0
License-File: LICENSE
Classifier: Development Status :: 4 - Beta
Classifier: Intended Audience :: Developers
Classifier: License :: OSI Approved :: Apache Software License
Classifier: Programming Language :: Python :: 3
Classifier: Programming Language :: Python :: 3.12
Requires-Python: >=3.12
Requires-Dist: jinja2>=3.1.0
Requires-Dist: python-multipart>=0.0.12
Requires-Dist: starlette>=0.41.0
